ipaddresses/appinfo.py
ipaddresses/AUTHORS.txt
ipaddresses/banner.txt
ipaddresses/banner_pt.txt
ipaddresses/ChangeLog.txt
ipaddresses/cli.py
ipaddresses/common.py
ipaddresses/gui_tk_func.py
ipaddresses/ipaddresses.py
ipaddresses/LICENSE.txt
ipaddresses/localization.py
ipaddresses/README.txt
ipaddresses/shared.py
ipaddresses/usage.txt
ipaddresses/usage_pt.txt
ipaddresses/__init__.py
ipaddresses/doc/.buildinfo
ipaddresses/doc/authors.html
ipaddresses/doc/changelog.html
ipaddresses/doc/genindex.html
ipaddresses/doc/index.html
ipaddresses/doc/ipaddresses.pdf
ipaddresses/doc/license.html
ipaddresses/doc/objects.inv
ipaddresses/doc/py-modindex.html
ipaddresses/doc/readme.html
ipaddresses/doc/reference.html
ipaddresses/doc/search.html
ipaddresses/doc/searchindex.js
ipaddresses/doc/_modules/cli.html
ipaddresses/doc/_modules/common.html
ipaddresses/doc/_modules/gui_tk_func.html
ipaddresses/doc/_modules/index.html
ipaddresses/doc/_modules/ipaddresses.html
ipaddresses/doc/_modules/localization.html
ipaddresses/doc/_modules/shared.html
ipaddresses/doc/_sources/authors.txt
ipaddresses/doc/_sources/changelog.txt
ipaddresses/doc/_sources/index.txt
ipaddresses/doc/_sources/license.txt
ipaddresses/doc/_sources/readme.txt
ipaddresses/doc/_sources/reference.txt
ipaddresses/doc/_static/ajax-loader.gif
ipaddresses/doc/_static/alabaster.css
ipaddresses/doc/_static/basic.css
ipaddresses/doc/_static/comment-bright.png
ipaddresses/doc/_static/comment-close.png
ipaddresses/doc/_static/comment.png
ipaddresses/doc/_static/doctools.js
ipaddresses/doc/_static/down-pressed.png
ipaddresses/doc/_static/down.png
ipaddresses/doc/_static/file.png
ipaddresses/doc/_static/jquery-1.11.1.js
ipaddresses/doc/_static/jquery.js
ipaddresses/doc/_static/minus.png
ipaddresses/doc/_static/plus.png
ipaddresses/doc/_static/pygments.css
ipaddresses/doc/_static/searchtools.js
ipaddresses/doc/_static/underscore-1.3.1.js
ipaddresses/doc/_static/underscore.js
ipaddresses-0.0.2.dist-info/DESCRIPTION.rst
ipaddresses-0.0.2.dist-info/entry_points.txt
ipaddresses-0.0.2.dist-info/METADATA
ipaddresses-0.0.2.dist-info/metadata.json
ipaddresses-0.0.2.dist-info/RECORD
ipaddresses-0.0.2.dist-info/top_level.txt
ipaddresses-0.0.2.dist-info/WHEEL
